easy_thread/__init__.py
easy_thread/easy_thread_core.py
easy_thread/easy_thread_utils.py
easy_thread-0.3.dist-info/METADATA
easy_thread-0.3.dist-info/WHEEL
easy_thread-0.3.dist-info/top_level.txt
easy_thread-0.3.dist-info/RECORD
