Metadata-Version: 2.1
Name: easy-thread
Version: 0.3
Summary: Module to make easy threads. 
Home-page: UNKNOWN
Author: UNKNOWN
Author-email: vanproskur@gmail.com
License: UNKNOWN
Platform: UNKNOWN
